suou/__init__.py
suou/asgi.py
suou/bits.py
suou/calendar.py
suou/classtools.py
suou/codecs.py
suou/collections.py
suou/color.py
suou/configparse.py
suou/dei.py
suou/dorks.py
suou/exceptions.py
suou/flask.py
suou/flask_restx.py
suou/flask_sqlalchemy.py
suou/functools.py
suou/glue.py
suou/http.py
suou/i18n.py
suou/iding.py
suou/itertools.py
suou/legal.py
suou/lex.py
suou/luck.py
suou/markdown.py
suou/mat.py
suou/migrate.py
suou/peewee.py
suou/quart.py
suou/quart_auth.py
suou/redact.py
suou/sass.py
suou/signing.py
suou/snowflake.py
suou/sqlalchemy_async.py
suou/strtools.py
suou/terminal.py
suou/validators.py
suou/waiter.py
suou/obsolete/__init__.py
suou/obsolete/configparsev0_3.py
suou/sqlalchemy/__init__.py
suou/sqlalchemy/asyncio.py
suou/sqlalchemy/orm.py
suou/sqlalchemy/quart.py
sakuragasaki46_suou-0.12.2.dist-info/METADATA
sakuragasaki46_suou-0.12.2.dist-info/WHEEL
sakuragasaki46_suou-0.12.2.dist-info/top_level.txt
sakuragasaki46_suou-0.12.2.dist-info/RECORD
