Metadata-Version: 2.4
Name: sakuragasaki46_suou
Version: 0.12.2
Summary: casual utility library for coding QoL
Author: Sakuragasaki46
License-Expression: Apache-2.0
Project-URL: Repository, https://nekode.yusur.moe/yusur/suou
Project-URL: Documentation, https://suou.readthedocs.io
Classifier: Development Status :: 2 - Pre-Alpha
Classifier: Programming Language :: Python :: 3
Classifier: Programming Language :: Python :: 3.10
Classifier: Programming Language :: Python :: 3.11
Classifier: Programming Language :: Python :: 3.12
Classifier: Programming Language :: Python :: 3.13
Classifier: Programming Language :: Python :: 3.14
Requires-Python: >=3.10
Requires-Dist: suou==0.12.2
Requires-Dist: itsdangerous
Requires-Dist: toml
Requires-Dist: pydantic
Requires-Dist: setuptools>=78.0.0
Requires-Dist: uvloop; os_name == "posix"
Provides-Extra: sqlalchemy
Requires-Dist: SQLAlchemy[asyncio]>=2.0.0; extra == "sqlalchemy"
Provides-Extra: flask
Requires-Dist: Flask>=2.0.0; extra == "flask"
Requires-Dist: Flask-RestX; extra == "flask"
Provides-Extra: flask-sqlalchemy
Requires-Dist: sakuragasaki46_suou[sqlalchemy]; extra == "flask-sqlalchemy"
Requires-Dist: sakuragasaki46_suou[flask]; extra == "flask-sqlalchemy"
Provides-Extra: peewee
Requires-Dist: peewee>=3.0.0; extra == "peewee"
Provides-Extra: markdown
Requires-Dist: markdown>=3.0.0; extra == "markdown"
Provides-Extra: quart
Requires-Dist: Quart; extra == "quart"
Requires-Dist: Quart-Schema; extra == "quart"
Requires-Dist: starlette>=0.47.2; extra == "quart"
Provides-Extra: quart-auth
Requires-Dist: sakuragasaki46_suou[quart_sqlalchemy]; extra == "quart-auth"
Requires-Dist: Quart-Auth; extra == "quart-auth"
Provides-Extra: quart-sqlalchemy
Requires-Dist: sakuragasaki46_suou[quart]; extra == "quart-sqlalchemy"
Requires-Dist: sakuragasaki46_suou[sqlalchemy]; extra == "quart-sqlalchemy"
Requires-Dist: flask-sqlalchemy; extra == "quart-sqlalchemy"
Provides-Extra: sass
Requires-Dist: libsass; extra == "sass"
Provides-Extra: full
Requires-Dist: sakuragasaki46_suou[flask]; extra == "full"
Requires-Dist: sakuragasaki46_suou[quart_auth]; extra == "full"
Requires-Dist: sakuragasaki46_suou[peewee]; extra == "full"
Requires-Dist: sakuragasaki46_suou[markdown]; extra == "full"
Requires-Dist: sakuragasaki46_suou[sass]; extra == "full"
Provides-Extra: docs
Requires-Dist: sphinx>=2.1; extra == "docs"
Requires-Dist: myst_parser; extra == "docs"
Requires-Dist: sphinx_rtd_theme; extra == "docs"
